<?xml version="1.0" encoding="utf-8"?>
<config>
  <other>
    <data>
      <open_level>80</open_level>
      <scene_id>9050</scene_id>
      <dead_max_count>8</dead_max_count>
      <lucky_interval>120</lucky_interval>
      <lucky_item>
        <item_id>28894</item_id>
        <num>1</num>
        <is_bind>1</is_bind>
      </lucky_item>
      <gongji_guwu_gold>5</gongji_guwu_gold>
      <gongji_guwu_max_per>50</gongji_guwu_max_per>
      <gongji_guwu_add_per>5</gongji_guwu_add_per>
      <hp_guwu_gold>2</hp_guwu_gold>
      <hp_guwu_max_per>50</hp_guwu_max_per>
      <hp_guwu_add_per>5</hp_guwu_add_per>
      <kill_honor>15</kill_honor>
      <broast_role_num_interval>2</broast_role_num_interval>
      <broact_title_id>7012</broact_title_id>
      <gather_id>337</gather_id>
      <gather_num>10</gather_num>
      <first_refresh_interval>5</first_refresh_interval>
      <refresh_interval>60</refresh_interval>
      <gather_time>2</gather_time>
      <gather_exit_time>60</gather_exit_time>
    </data>
  </other>
  <realive_pos_list>
    <data>
      <realive_pos_x>66</realive_pos_x>
      <realive_pos_y>57</realive_pos_y>
    </data>
    <data>
      <realive_pos_x>40</realive_pos_x>
      <realive_pos_y>59</realive_pos_y>
    </data>
    <data>
      <realive_pos_x>89</realive_pos_x>
      <realive_pos_y>102</realive_pos_y>
    </data>
    <data>
      <realive_pos_x>79</realive_pos_x>
      <realive_pos_y>57</realive_pos_y>
    </data>
    <data>
      <realive_pos_x>35</realive_pos_x>
      <realive_pos_y>79</realive_pos_y>
    </data>
    <data>
      <realive_pos_x>57</realive_pos_x>
      <realive_pos_y>55</realive_pos_y>
    </data>
    <data>
      <realive_pos_x>95</realive_pos_x>
      <realive_pos_y>73</realive_pos_y>
    </data>
    <data>
      <realive_pos_x>48</realive_pos_x>
      <realive_pos_y>101</realive_pos_y>
    </data>
  </realive_pos_list>
  <kill_rank_reward>
    <data>
      <rank>0</rank>
      <reward_item_list>
        <reward_item>
          <item_id>28894</item_id>
          <num>6</num>
          <is_bind>1</is_bind>
        </reward_item>
        <reward_item>
          <item_id>26504</item_id>
          <num>50</num>
          <is_bind>1</is_bind>
        </reward_item>
      </reward_item_list>
    </data>
    <data>
      <rank>1</rank>
      <reward_item_list>
        <reward_item>
          <item_id>28894</item_id>
          <num>5</num>
          <is_bind>1</is_bind>
        </reward_item>
        <reward_item>
          <item_id>26504</item_id>
          <num>40</num>
          <is_bind>1</is_bind>
        </reward_item>
      </reward_item_list>
    </data>
    <data>
      <rank>2</rank>
      <reward_item_list>
        <reward_item>
          <item_id>28894</item_id>
          <num>4</num>
          <is_bind>1</is_bind>
        </reward_item>
        <reward_item>
          <item_id>26504</item_id>
          <num>30</num>
          <is_bind>1</is_bind>
        </reward_item>
      </reward_item_list>
    </data>
    <data>
      <rank>3</rank>
      <reward_item_list>
        <reward_item>
          <item_id>28894</item_id>
          <num>3</num>
          <is_bind>1</is_bind>
        </reward_item>
        <reward_item>
          <item_id>26504</item_id>
          <num>30</num>
          <is_bind>1</is_bind>
        </reward_item>
      </reward_item_list>
    </data>
    <data>
      <rank>4</rank>
      <reward_item_list>
        <reward_item>
          <item_id>28894</item_id>
          <num>3</num>
          <is_bind>1</is_bind>
        </reward_item>
        <reward_item>
          <item_id>26504</item_id>
          <num>30</num>
          <is_bind>1</is_bind>
        </reward_item>
      </reward_item_list>
    </data>
    <data>
      <rank>5</rank>
      <reward_item_list>
        <reward_item>
          <item_id>28894</item_id>
          <num>3</num>
          <is_bind>1</is_bind>
        </reward_item>
        <reward_item>
          <item_id>26504</item_id>
          <num>30</num>
          <is_bind>1</is_bind>
        </reward_item>
      </reward_item_list>
    </data>
    <data>
      <rank>6</rank>
      <reward_item_list>
        <reward_item>
          <item_id>28894</item_id>
          <num>3</num>
          <is_bind>1</is_bind>
        </reward_item>
        <reward_item>
          <item_id>26504</item_id>
          <num>30</num>
          <is_bind>1</is_bind>
        </reward_item>
      </reward_item_list>
    </data>
    <data>
      <rank>7</rank>
      <reward_item_list>
        <reward_item>
          <item_id>28894</item_id>
          <num>3</num>
          <is_bind>1</is_bind>
        </reward_item>
        <reward_item>
          <item_id>26504</item_id>
          <num>30</num>
          <is_bind>1</is_bind>
        </reward_item>
      </reward_item_list>
    </data>
    <data>
      <rank>8</rank>
      <reward_item_list>
        <reward_item>
          <item_id>28894</item_id>
          <num>3</num>
          <is_bind>1</is_bind>
        </reward_item>
        <reward_item>
          <item_id>26504</item_id>
          <num>30</num>
          <is_bind>1</is_bind>
        </reward_item>
      </reward_item_list>
    </data>
    <data>
      <rank>9</rank>
      <reward_item_list>
        <reward_item>
          <item_id>28894</item_id>
          <num>3</num>
          <is_bind>1</is_bind>
        </reward_item>
        <reward_item>
          <item_id>26504</item_id>
          <num>30</num>
          <is_bind>1</is_bind>
        </reward_item>
      </reward_item_list>
    </data>
    <data>
      <rank>10</rank>
      <reward_item_list>
        <reward_item>
          <item_id>28894</item_id>
          <num>3</num>
          <is_bind>1</is_bind>
        </reward_item>
        <reward_item>
          <item_id>26504</item_id>
          <num>30</num>
          <is_bind>1</is_bind>
        </reward_item>
      </reward_item_list>
    </data>
    <data>
      <rank>11</rank>
      <reward_item_list>
        <reward_item>
          <item_id>28894</item_id>
          <num>3</num>
          <is_bind>1</is_bind>
        </reward_item>
        <reward_item>
          <item_id>26504</item_id>
          <num>30</num>
          <is_bind>1</is_bind>
        </reward_item>
      </reward_item_list>
    </data>
    <data>
      <rank>12</rank>
      <reward_item_list>
        <reward_item>
          <item_id>28894</item_id>
          <num>3</num>
          <is_bind>1</is_bind>
        </reward_item>
        <reward_item>
          <item_id>26504</item_id>
          <num>30</num>
          <is_bind>1</is_bind>
        </reward_item>
      </reward_item_list>
    </data>
    <data>
      <rank>13</rank>
      <reward_item_list>
        <reward_item>
          <item_id>28894</item_id>
          <num>3</num>
          <is_bind>1</is_bind>
        </reward_item>
        <reward_item>
          <item_id>26504</item_id>
          <num>30</num>
          <is_bind>1</is_bind>
        </reward_item>
      </reward_item_list>
    </data>
    <data>
      <rank>14</rank>
      <reward_item_list>
        <reward_item>
          <item_id>28894</item_id>
          <num>3</num>
          <is_bind>1</is_bind>
        </reward_item>
        <reward_item>
          <item_id>26504</item_id>
          <num>30</num>
          <is_bind>1</is_bind>
        </reward_item>
      </reward_item_list>
    </data>
    <data>
      <rank>15</rank>
      <reward_item_list>
        <reward_item>
          <item_id>28894</item_id>
          <num>3</num>
          <is_bind>1</is_bind>
        </reward_item>
        <reward_item>
          <item_id>26504</item_id>
          <num>30</num>
          <is_bind>1</is_bind>
        </reward_item>
      </reward_item_list>
    </data>
    <data>
      <rank>16</rank>
      <reward_item_list>
        <reward_item>
          <item_id>28894</item_id>
          <num>3</num>
          <is_bind>1</is_bind>
        </reward_item>
        <reward_item>
          <item_id>26504</item_id>
          <num>30</num>
          <is_bind>1</is_bind>
        </reward_item>
      </reward_item_list>
    </data>
    <data>
      <rank>17</rank>
      <reward_item_list>
        <reward_item>
          <item_id>28894</item_id>
          <num>3</num>
          <is_bind>1</is_bind>
        </reward_item>
        <reward_item>
          <item_id>26504</item_id>
          <num>30</num>
          <is_bind>1</is_bind>
        </reward_item>
      </reward_item_list>
    </data>
    <data>
      <rank>18</rank>
      <reward_item_list>
        <reward_item>
          <item_id>28894</item_id>
          <num>3</num>
          <is_bind>1</is_bind>
        </reward_item>
        <reward_item>
          <item_id>26504</item_id>
          <num>30</num>
          <is_bind>1</is_bind>
        </reward_item>
      </reward_item_list>
    </data>
    <data>
      <rank>19</rank>
      <reward_item_list>
        <reward_item>
          <item_id>28894</item_id>
          <num>3</num>
          <is_bind>1</is_bind>
        </reward_item>
        <reward_item>
          <item_id>26504</item_id>
          <num>30</num>
          <is_bind>1</is_bind>
        </reward_item>
      </reward_item_list>
    </data>
    <data>
      <rank>20</rank>
      <reward_item_list>
        <reward_item>
          <item_id>28894</item_id>
          <num>3</num>
          <is_bind>1</is_bind>
        </reward_item>
        <reward_item>
          <item_id>26504</item_id>
          <num>30</num>
          <is_bind>1</is_bind>
        </reward_item>
      </reward_item_list>
    </data>
    <data>
      <rank>21</rank>
      <reward_item_list>
        <reward_item>
          <item_id>28894</item_id>
          <num>3</num>
          <is_bind>1</is_bind>
        </reward_item>
        <reward_item>
          <item_id>26504</item_id>
          <num>30</num>
          <is_bind>1</is_bind>
        </reward_item>
      </reward_item_list>
    </data>
    <data>
      <rank>22</rank>
      <reward_item_list>
        <reward_item>
          <item_id>28894</item_id>
          <num>3</num>
          <is_bind>1</is_bind>
        </reward_item>
        <reward_item>
          <item_id>26504</item_id>
          <num>30</num>
          <is_bind>1</is_bind>
        </reward_item>
      </reward_item_list>
    </data>
    <data>
      <rank>23</rank>
      <reward_item_list>
        <reward_item>
          <item_id>28894</item_id>
          <num>3</num>
          <is_bind>1</is_bind>
        </reward_item>
        <reward_item>
          <item_id>26504</item_id>
          <num>30</num>
          <is_bind>1</is_bind>
        </reward_item>
      </reward_item_list>
    </data>
    <data>
      <rank>24</rank>
      <reward_item_list>
        <reward_item>
          <item_id>28894</item_id>
          <num>3</num>
          <is_bind>1</is_bind>
        </reward_item>
        <reward_item>
          <item_id>26504</item_id>
          <num>30</num>
          <is_bind>1</is_bind>
        </reward_item>
      </reward_item_list>
    </data>
    <data>
      <rank>25</rank>
      <reward_item_list>
        <reward_item>
          <item_id>28894</item_id>
          <num>3</num>
          <is_bind>1</is_bind>
        </reward_item>
        <reward_item>
          <item_id>26504</item_id>
          <num>30</num>
          <is_bind>1</is_bind>
        </reward_item>
      </reward_item_list>
    </data>
    <data>
      <rank>26</rank>
      <reward_item_list>
        <reward_item>
          <item_id>28894</item_id>
          <num>3</num>
          <is_bind>1</is_bind>
        </reward_item>
        <reward_item>
          <item_id>26504</item_id>
          <num>30</num>
          <is_bind>1</is_bind>
        </reward_item>
      </reward_item_list>
    </data>
    <data>
      <rank>27</rank>
      <reward_item_list>
        <reward_item>
          <item_id>28894</item_id>
          <num>3</num>
          <is_bind>1</is_bind>
        </reward_item>
        <reward_item>
          <item_id>26504</item_id>
          <num>30</num>
          <is_bind>1</is_bind>
        </reward_item>
      </reward_item_list>
    </data>
    <data>
      <rank>28</rank>
      <reward_item_list>
        <reward_item>
          <item_id>28894</item_id>
          <num>3</num>
          <is_bind>1</is_bind>
        </reward_item>
        <reward_item>
          <item_id>26504</item_id>
          <num>30</num>
          <is_bind>1</is_bind>
        </reward_item>
      </reward_item_list>
    </data>
    <data>
      <rank>29</rank>
      <reward_item_list>
        <reward_item>
          <item_id>28894</item_id>
          <num>3</num>
          <is_bind>1</is_bind>
        </reward_item>
        <reward_item>
          <item_id>26504</item_id>
          <num>30</num>
          <is_bind>1</is_bind>
        </reward_item>
      </reward_item_list>
    </data>
    <data>
      <rank>30</rank>
      <reward_item_list>
        <reward_item>
          <item_id>28894</item_id>
          <num>3</num>
          <is_bind>1</is_bind>
        </reward_item>
        <reward_item>
          <item_id>26504</item_id>
          <num>30</num>
          <is_bind>1</is_bind>
        </reward_item>
      </reward_item_list>
    </data>
    <data>
      <rank>31</rank>
      <reward_item_list>
        <reward_item>
          <item_id>28894</item_id>
          <num>3</num>
          <is_bind>1</is_bind>
        </reward_item>
        <reward_item>
          <item_id>26504</item_id>
          <num>30</num>
          <is_bind>1</is_bind>
        </reward_item>
      </reward_item_list>
    </data>
    <data>
      <rank>32</rank>
      <reward_item_list>
        <reward_item>
          <item_id>28894</item_id>
          <num>3</num>
          <is_bind>1</is_bind>
        </reward_item>
        <reward_item>
          <item_id>26504</item_id>
          <num>30</num>
          <is_bind>1</is_bind>
        </reward_item>
      </reward_item_list>
    </data>
    <data>
      <rank>33</rank>
      <reward_item_list>
        <reward_item>
          <item_id>28894</item_id>
          <num>3</num>
          <is_bind>1</is_bind>
        </reward_item>
        <reward_item>
          <item_id>26504</item_id>
          <num>30</num>
          <is_bind>1</is_bind>
        </reward_item>
      </reward_item_list>
    </data>
    <data>
      <rank>34</rank>
      <reward_item_list>
        <reward_item>
          <item_id>28894</item_id>
          <num>3</num>
          <is_bind>1</is_bind>
        </reward_item>
        <reward_item>
          <item_id>26504</item_id>
          <num>30</num>
          <is_bind>1</is_bind>
        </reward_item>
      </reward_item_list>
    </data>
    <data>
      <rank>35</rank>
      <reward_item_list>
        <reward_item>
          <item_id>28894</item_id>
          <num>3</num>
          <is_bind>1</is_bind>
        </reward_item>
        <reward_item>
          <item_id>26504</item_id>
          <num>30</num>
          <is_bind>1</is_bind>
        </reward_item>
      </reward_item_list>
    </data>
    <data>
      <rank>36</rank>
      <reward_item_list>
        <reward_item>
          <item_id>28894</item_id>
          <num>3</num>
          <is_bind>1</is_bind>
        </reward_item>
        <reward_item>
          <item_id>26504</item_id>
          <num>30</num>
          <is_bind>1</is_bind>
        </reward_item>
      </reward_item_list>
    </data>
    <data>
      <rank>37</rank>
      <reward_item_list>
        <reward_item>
          <item_id>28894</item_id>
          <num>3</num>
          <is_bind>1</is_bind>
        </reward_item>
        <reward_item>
          <item_id>26504</item_id>
          <num>30</num>
          <is_bind>1</is_bind>
        </reward_item>
      </reward_item_list>
    </data>
    <data>
      <rank>38</rank>
      <reward_item_list>
        <reward_item>
          <item_id>28894</item_id>
          <num>3</num>
          <is_bind>1</is_bind>
        </reward_item>
        <reward_item>
          <item_id>26504</item_id>
          <num>30</num>
          <is_bind>1</is_bind>
        </reward_item>
      </reward_item_list>
    </data>
    <data>
      <rank>39</rank>
      <reward_item_list>
        <reward_item>
          <item_id>28894</item_id>
          <num>3</num>
          <is_bind>1</is_bind>
        </reward_item>
        <reward_item>
          <item_id>26504</item_id>
          <num>30</num>
          <is_bind>1</is_bind>
        </reward_item>
      </reward_item_list>
    </data>
    <data>
      <rank>40</rank>
      <reward_item_list>
        <reward_item>
          <item_id>28894</item_id>
          <num>3</num>
          <is_bind>1</is_bind>
        </reward_item>
        <reward_item>
          <item_id>26504</item_id>
          <num>30</num>
          <is_bind>1</is_bind>
        </reward_item>
      </reward_item_list>
    </data>
    <data>
      <rank>41</rank>
      <reward_item_list>
        <reward_item>
          <item_id>28894</item_id>
          <num>3</num>
          <is_bind>1</is_bind>
        </reward_item>
        <reward_item>
          <item_id>26504</item_id>
          <num>30</num>
          <is_bind>1</is_bind>
        </reward_item>
      </reward_item_list>
    </data>
    <data>
      <rank>42</rank>
      <reward_item_list>
        <reward_item>
          <item_id>28894</item_id>
          <num>3</num>
          <is_bind>1</is_bind>
        </reward_item>
        <reward_item>
          <item_id>26504</item_id>
          <num>30</num>
          <is_bind>1</is_bind>
        </reward_item>
      </reward_item_list>
    </data>
    <data>
      <rank>43</rank>
      <reward_item_list>
        <reward_item>
          <item_id>28894</item_id>
          <num>3</num>
          <is_bind>1</is_bind>
        </reward_item>
        <reward_item>
          <item_id>26504</item_id>
          <num>30</num>
          <is_bind>1</is_bind>
        </reward_item>
      </reward_item_list>
    </data>
    <data>
      <rank>44</rank>
      <reward_item_list>
        <reward_item>
          <item_id>28894</item_id>
          <num>3</num>
          <is_bind>1</is_bind>
        </reward_item>
        <reward_item>
          <item_id>26504</item_id>
          <num>30</num>
          <is_bind>1</is_bind>
        </reward_item>
      </reward_item_list>
    </data>
    <data>
      <rank>45</rank>
      <reward_item_list>
        <reward_item>
          <item_id>28894</item_id>
          <num>3</num>
          <is_bind>1</is_bind>
        </reward_item>
        <reward_item>
          <item_id>26504</item_id>
          <num>30</num>
          <is_bind>1</is_bind>
        </reward_item>
      </reward_item_list>
    </data>
    <data>
      <rank>46</rank>
      <reward_item_list>
        <reward_item>
          <item_id>28894</item_id>
          <num>3</num>
          <is_bind>1</is_bind>
        </reward_item>
        <reward_item>
          <item_id>26504</item_id>
          <num>30</num>
          <is_bind>1</is_bind>
        </reward_item>
      </reward_item_list>
    </data>
    <data>
      <rank>47</rank>
      <reward_item_list>
        <reward_item>
          <item_id>28894</item_id>
          <num>3</num>
          <is_bind>1</is_bind>
        </reward_item>
        <reward_item>
          <item_id>26504</item_id>
          <num>30</num>
          <is_bind>1</is_bind>
        </reward_item>
      </reward_item_list>
    </data>
    <data>
      <rank>48</rank>
      <reward_item_list>
        <reward_item>
          <item_id>28894</item_id>
          <num>3</num>
          <is_bind>1</is_bind>
        </reward_item>
        <reward_item>
          <item_id>26504</item_id>
          <num>30</num>
          <is_bind>1</is_bind>
        </reward_item>
      </reward_item_list>
    </data>
    <data>
      <rank>49</rank>
      <reward_item_list>
        <reward_item>
          <item_id>28894</item_id>
          <num>3</num>
          <is_bind>1</is_bind>
        </reward_item>
        <reward_item>
          <item_id>26504</item_id>
          <num>30</num>
          <is_bind>1</is_bind>
        </reward_item>
      </reward_item_list>
    </data>
    <data>
      <rank>50</rank>
      <reward_item_list>
        <reward_item>
          <item_id>28894</item_id>
          <num>3</num>
          <is_bind>1</is_bind>
        </reward_item>
        <reward_item>
          <item_id>26504</item_id>
          <num>30</num>
          <is_bind>1</is_bind>
        </reward_item>
      </reward_item_list>
    </data>
    <data>
      <rank>51</rank>
      <reward_item_list>
        <reward_item>
          <item_id>28894</item_id>
          <num>3</num>
          <is_bind>1</is_bind>
        </reward_item>
        <reward_item>
          <item_id>26504</item_id>
          <num>30</num>
          <is_bind>1</is_bind>
        </reward_item>
      </reward_item_list>
    </data>
    <data>
      <rank>52</rank>
      <reward_item_list>
        <reward_item>
          <item_id>28894</item_id>
          <num>3</num>
          <is_bind>1</is_bind>
        </reward_item>
        <reward_item>
          <item_id>26504</item_id>
          <num>30</num>
          <is_bind>1</is_bind>
        </reward_item>
      </reward_item_list>
    </data>
    <data>
      <rank>53</rank>
      <reward_item_list>
        <reward_item>
          <item_id>28894</item_id>
          <num>3</num>
          <is_bind>1</is_bind>
        </reward_item>
        <reward_item>
          <item_id>26504</item_id>
          <num>30</num>
          <is_bind>1</is_bind>
        </reward_item>
      </reward_item_list>
    </data>
    <data>
      <rank>54</rank>
      <reward_item_list>
        <reward_item>
          <item_id>28894</item_id>
          <num>3</num>
          <is_bind>1</is_bind>
        </reward_item>
        <reward_item>
          <item_id>26504</item_id>
          <num>30</num>
          <is_bind>1</is_bind>
        </reward_item>
      </reward_item_list>
    </data>
    <data>
      <rank>55</rank>
      <reward_item_list>
        <reward_item>
          <item_id>28894</item_id>
          <num>3</num>
          <is_bind>1</is_bind>
        </reward_item>
        <reward_item>
          <item_id>26504</item_id>
          <num>30</num>
          <is_bind>1</is_bind>
        </reward_item>
      </reward_item_list>
    </data>
    <data>
      <rank>56</rank>
      <reward_item_list>
        <reward_item>
          <item_id>28894</item_id>
          <num>3</num>
          <is_bind>1</is_bind>
        </reward_item>
        <reward_item>
          <item_id>26504</item_id>
          <num>30</num>
          <is_bind>1</is_bind>
        </reward_item>
      </reward_item_list>
    </data>
    <data>
      <rank>57</rank>
      <reward_item_list>
        <reward_item>
          <item_id>28894</item_id>
          <num>3</num>
          <is_bind>1</is_bind>
        </reward_item>
        <reward_item>
          <item_id>26504</item_id>
          <num>30</num>
          <is_bind>1</is_bind>
        </reward_item>
      </reward_item_list>
    </data>
    <data>
      <rank>58</rank>
      <reward_item_list>
        <reward_item>
          <item_id>28894</item_id>
          <num>3</num>
          <is_bind>1</is_bind>
        </reward_item>
        <reward_item>
          <item_id>26504</item_id>
          <num>30</num>
          <is_bind>1</is_bind>
        </reward_item>
      </reward_item_list>
    </data>
    <data>
      <rank>59</rank>
      <reward_item_list>
        <reward_item>
          <item_id>28894</item_id>
          <num>3</num>
          <is_bind>1</is_bind>
        </reward_item>
        <reward_item>
          <item_id>26504</item_id>
          <num>30</num>
          <is_bind>1</is_bind>
        </reward_item>
      </reward_item_list>
    </data>
    <data>
      <rank>60</rank>
      <reward_item_list>
        <reward_item>
          <item_id>28894</item_id>
          <num>3</num>
          <is_bind>1</is_bind>
        </reward_item>
        <reward_item>
          <item_id>26504</item_id>
          <num>30</num>
          <is_bind>1</is_bind>
        </reward_item>
      </reward_item_list>
    </data>
    <data>
      <rank>61</rank>
      <reward_item_list>
        <reward_item>
          <item_id>28894</item_id>
          <num>3</num>
          <is_bind>1</is_bind>
        </reward_item>
        <reward_item>
          <item_id>26504</item_id>
          <num>30</num>
          <is_bind>1</is_bind>
        </reward_item>
      </reward_item_list>
    </data>
    <data>
      <rank>62</rank>
      <reward_item_list>
        <reward_item>
          <item_id>28894</item_id>
          <num>3</num>
          <is_bind>1</is_bind>
        </reward_item>
        <reward_item>
          <item_id>26504</item_id>
          <num>30</num>
          <is_bind>1</is_bind>
        </reward_item>
      </reward_item_list>
    </data>
    <data>
      <rank>63</rank>
      <reward_item_list>
        <reward_item>
          <item_id>28894</item_id>
          <num>3</num>
          <is_bind>1</is_bind>
        </reward_item>
        <reward_item>
          <item_id>26504</item_id>
          <num>30</num>
          <is_bind>1</is_bind>
        </reward_item>
      </reward_item_list>
    </data>
    <data>
      <rank>64</rank>
      <reward_item_list>
        <reward_item>
          <item_id>28894</item_id>
          <num>3</num>
          <is_bind>1</is_bind>
        </reward_item>
        <reward_item>
          <item_id>26504</item_id>
          <num>30</num>
          <is_bind>1</is_bind>
        </reward_item>
      </reward_item_list>
    </data>
    <data>
      <rank>65</rank>
      <reward_item_list>
        <reward_item>
          <item_id>28894</item_id>
          <num>3</num>
          <is_bind>1</is_bind>
        </reward_item>
        <reward_item>
          <item_id>26504</item_id>
          <num>30</num>
          <is_bind>1</is_bind>
        </reward_item>
      </reward_item_list>
    </data>
    <data>
      <rank>66</rank>
      <reward_item_list>
        <reward_item>
          <item_id>28894</item_id>
          <num>3</num>
          <is_bind>1</is_bind>
        </reward_item>
        <reward_item>
          <item_id>26504</item_id>
          <num>30</num>
          <is_bind>1</is_bind>
        </reward_item>
      </reward_item_list>
    </data>
    <data>
      <rank>67</rank>
      <reward_item_list>
        <reward_item>
          <item_id>28894</item_id>
          <num>3</num>
          <is_bind>1</is_bind>
        </reward_item>
        <reward_item>
          <item_id>26504</item_id>
          <num>30</num>
          <is_bind>1</is_bind>
        </reward_item>
      </reward_item_list>
    </data>
    <data>
      <rank>68</rank>
      <reward_item_list>
        <reward_item>
          <item_id>28894</item_id>
          <num>3</num>
          <is_bind>1</is_bind>
        </reward_item>
        <reward_item>
          <item_id>26504</item_id>
          <num>30</num>
          <is_bind>1</is_bind>
        </reward_item>
      </reward_item_list>
    </data>
    <data>
      <rank>69</rank>
      <reward_item_list>
        <reward_item>
          <item_id>28894</item_id>
          <num>3</num>
          <is_bind>1</is_bind>
        </reward_item>
        <reward_item>
          <item_id>26504</item_id>
          <num>30</num>
          <is_bind>1</is_bind>
        </reward_item>
      </reward_item_list>
    </data>
    <data>
      <rank>70</rank>
      <reward_item_list>
        <reward_item>
          <item_id>28894</item_id>
          <num>3</num>
          <is_bind>1</is_bind>
        </reward_item>
        <reward_item>
          <item_id>26504</item_id>
          <num>30</num>
          <is_bind>1</is_bind>
        </reward_item>
      </reward_item_list>
    </data>
    <data>
      <rank>71</rank>
      <reward_item_list>
        <reward_item>
          <item_id>28894</item_id>
          <num>3</num>
          <is_bind>1</is_bind>
        </reward_item>
        <reward_item>
          <item_id>26504</item_id>
          <num>30</num>
          <is_bind>1</is_bind>
        </reward_item>
      </reward_item_list>
    </data>
    <data>
      <rank>72</rank>
      <reward_item_list>
        <reward_item>
          <item_id>28894</item_id>
          <num>3</num>
          <is_bind>1</is_bind>
        </reward_item>
        <reward_item>
          <item_id>26504</item_id>
          <num>30</num>
          <is_bind>1</is_bind>
        </reward_item>
      </reward_item_list>
    </data>
    <data>
      <rank>73</rank>
      <reward_item_list>
        <reward_item>
          <item_id>28894</item_id>
          <num>3</num>
          <is_bind>1</is_bind>
        </reward_item>
        <reward_item>
          <item_id>26504</item_id>
          <num>30</num>
          <is_bind>1</is_bind>
        </reward_item>
      </reward_item_list>
    </data>
    <data>
      <rank>74</rank>
      <reward_item_list>
        <reward_item>
          <item_id>28894</item_id>
          <num>3</num>
          <is_bind>1</is_bind>
        </reward_item>
        <reward_item>
          <item_id>26504</item_id>
          <num>30</num>
          <is_bind>1</is_bind>
        </reward_item>
      </reward_item_list>
    </data>
    <data>
      <rank>75</rank>
      <reward_item_list>
        <reward_item>
          <item_id>28894</item_id>
          <num>3</num>
          <is_bind>1</is_bind>
        </reward_item>
        <reward_item>
          <item_id>26504</item_id>
          <num>30</num>
          <is_bind>1</is_bind>
        </reward_item>
      </reward_item_list>
    </data>
    <data>
      <rank>76</rank>
      <reward_item_list>
        <reward_item>
          <item_id>28894</item_id>
          <num>3</num>
          <is_bind>1</is_bind>
        </reward_item>
        <reward_item>
          <item_id>26504</item_id>
          <num>30</num>
          <is_bind>1</is_bind>
        </reward_item>
      </reward_item_list>
    </data>
    <data>
      <rank>77</rank>
      <reward_item_list>
        <reward_item>
          <item_id>28894</item_id>
          <num>3</num>
          <is_bind>1</is_bind>
        </reward_item>
        <reward_item>
          <item_id>26504</item_id>
          <num>30</num>
          <is_bind>1</is_bind>
        </reward_item>
      </reward_item_list>
    </data>
    <data>
      <rank>78</rank>
      <reward_item_list>
        <reward_item>
          <item_id>28894</item_id>
          <num>3</num>
          <is_bind>1</is_bind>
        </reward_item>
        <reward_item>
          <item_id>26504</item_id>
          <num>30</num>
          <is_bind>1</is_bind>
        </reward_item>
      </reward_item_list>
    </data>
    <data>
      <rank>79</rank>
      <reward_item_list>
        <reward_item>
          <item_id>28894</item_id>
          <num>3</num>
          <is_bind>1</is_bind>
        </reward_item>
        <reward_item>
          <item_id>26504</item_id>
          <num>30</num>
          <is_bind>1</is_bind>
        </reward_item>
      </reward_item_list>
    </data>
    <data>
      <rank>80</rank>
      <reward_item_list>
        <reward_item>
          <item_id>28894</item_id>
          <num>3</num>
          <is_bind>1</is_bind>
        </reward_item>
        <reward_item>
          <item_id>26504</item_id>
          <num>30</num>
          <is_bind>1</is_bind>
        </reward_item>
      </reward_item_list>
    </data>
    <data>
      <rank>81</rank>
      <reward_item_list>
        <reward_item>
          <item_id>28894</item_id>
          <num>3</num>
          <is_bind>1</is_bind>
        </reward_item>
        <reward_item>
          <item_id>26504</item_id>
          <num>30</num>
          <is_bind>1</is_bind>
        </reward_item>
      </reward_item_list>
    </data>
    <data>
      <rank>82</rank>
      <reward_item_list>
        <reward_item>
          <item_id>28894</item_id>
          <num>3</num>
          <is_bind>1</is_bind>
        </reward_item>
        <reward_item>
          <item_id>26504</item_id>
          <num>30</num>
          <is_bind>1</is_bind>
        </reward_item>
      </reward_item_list>
    </data>
    <data>
      <rank>83</rank>
      <reward_item_list>
        <reward_item>
          <item_id>28894</item_id>
          <num>3</num>
          <is_bind>1</is_bind>
        </reward_item>
        <reward_item>
          <item_id>26504</item_id>
          <num>30</num>
          <is_bind>1</is_bind>
        </reward_item>
      </reward_item_list>
    </data>
    <data>
      <rank>84</rank>
      <reward_item_list>
        <reward_item>
          <item_id>28894</item_id>
          <num>3</num>
          <is_bind>1</is_bind>
        </reward_item>
        <reward_item>
          <item_id>26504</item_id>
          <num>30</num>
          <is_bind>1</is_bind>
        </reward_item>
      </reward_item_list>
    </data>
    <data>
      <rank>85</rank>
      <reward_item_list>
        <reward_item>
          <item_id>28894</item_id>
          <num>3</num>
          <is_bind>1</is_bind>
        </reward_item>
        <reward_item>
          <item_id>26504</item_id>
          <num>30</num>
          <is_bind>1</is_bind>
        </reward_item>
      </reward_item_list>
    </data>
    <data>
      <rank>86</rank>
      <reward_item_list>
        <reward_item>
          <item_id>28894</item_id>
          <num>3</num>
          <is_bind>1</is_bind>
        </reward_item>
        <reward_item>
          <item_id>26504</item_id>
          <num>30</num>
          <is_bind>1</is_bind>
        </reward_item>
      </reward_item_list>
    </data>
    <data>
      <rank>87</rank>
      <reward_item_list>
        <reward_item>
          <item_id>28894</item_id>
          <num>3</num>
          <is_bind>1</is_bind>
        </reward_item>
        <reward_item>
          <item_id>26504</item_id>
          <num>30</num>
          <is_bind>1</is_bind>
        </reward_item>
      </reward_item_list>
    </data>
    <data>
      <rank>88</rank>
      <reward_item_list>
        <reward_item>
          <item_id>28894</item_id>
          <num>3</num>
          <is_bind>1</is_bind>
        </reward_item>
        <reward_item>
          <item_id>26504</item_id>
          <num>30</num>
          <is_bind>1</is_bind>
        </reward_item>
      </reward_item_list>
    </data>
    <data>
      <rank>89</rank>
      <reward_item_list>
        <reward_item>
          <item_id>28894</item_id>
          <num>3</num>
          <is_bind>1</is_bind>
        </reward_item>
        <reward_item>
          <item_id>26504</item_id>
          <num>30</num>
          <is_bind>1</is_bind>
        </reward_item>
      </reward_item_list>
    </data>
    <data>
      <rank>90</rank>
      <reward_item_list>
        <reward_item>
          <item_id>28894</item_id>
          <num>3</num>
          <is_bind>1</is_bind>
        </reward_item>
        <reward_item>
          <item_id>26504</item_id>
          <num>30</num>
          <is_bind>1</is_bind>
        </reward_item>
      </reward_item_list>
    </data>
    <data>
      <rank>91</rank>
      <reward_item_list>
        <reward_item>
          <item_id>28894</item_id>
          <num>3</num>
          <is_bind>1</is_bind>
        </reward_item>
        <reward_item>
          <item_id>26504</item_id>
          <num>30</num>
          <is_bind>1</is_bind>
        </reward_item>
      </reward_item_list>
    </data>
    <data>
      <rank>92</rank>
      <reward_item_list>
        <reward_item>
          <item_id>28894</item_id>
          <num>3</num>
          <is_bind>1</is_bind>
        </reward_item>
        <reward_item>
          <item_id>26504</item_id>
          <num>30</num>
          <is_bind>1</is_bind>
        </reward_item>
      </reward_item_list>
    </data>
    <data>
      <rank>93</rank>
      <reward_item_list>
        <reward_item>
          <item_id>28894</item_id>
          <num>3</num>
          <is_bind>1</is_bind>
        </reward_item>
        <reward_item>
          <item_id>26504</item_id>
          <num>30</num>
          <is_bind>1</is_bind>
        </reward_item>
      </reward_item_list>
    </data>
    <data>
      <rank>94</rank>
      <reward_item_list>
        <reward_item>
          <item_id>28894</item_id>
          <num>3</num>
          <is_bind>1</is_bind>
        </reward_item>
        <reward_item>
          <item_id>26504</item_id>
          <num>30</num>
          <is_bind>1</is_bind>
        </reward_item>
      </reward_item_list>
    </data>
    <data>
      <rank>95</rank>
      <reward_item_list>
        <reward_item>
          <item_id>28894</item_id>
          <num>3</num>
          <is_bind>1</is_bind>
        </reward_item>
        <reward_item>
          <item_id>26504</item_id>
          <num>30</num>
          <is_bind>1</is_bind>
        </reward_item>
      </reward_item_list>
    </data>
    <data>
      <rank>96</rank>
      <reward_item_list>
        <reward_item>
          <item_id>28894</item_id>
          <num>3</num>
          <is_bind>1</is_bind>
        </reward_item>
        <reward_item>
          <item_id>26504</item_id>
          <num>30</num>
          <is_bind>1</is_bind>
        </reward_item>
      </reward_item_list>
    </data>
    <data>
      <rank>97</rank>
      <reward_item_list>
        <reward_item>
          <item_id>28894</item_id>
          <num>3</num>
          <is_bind>1</is_bind>
        </reward_item>
        <reward_item>
          <item_id>26504</item_id>
          <num>30</num>
          <is_bind>1</is_bind>
        </reward_item>
      </reward_item_list>
    </data>
    <data>
      <rank>98</rank>
      <reward_item_list>
        <reward_item>
          <item_id>28894</item_id>
          <num>3</num>
          <is_bind>1</is_bind>
        </reward_item>
        <reward_item>
          <item_id>26504</item_id>
          <num>30</num>
          <is_bind>1</is_bind>
        </reward_item>
      </reward_item_list>
    </data>
    <data>
      <rank>99</rank>
      <reward_item_list>
        <reward_item>
          <item_id>28894</item_id>
          <num>3</num>
          <is_bind>1</is_bind>
        </reward_item>
        <reward_item>
          <item_id>26504</item_id>
          <num>30</num>
          <is_bind>1</is_bind>
        </reward_item>
      </reward_item_list>
    </data>
    <data>
      <rank>100</rank>
      <reward_item_list>
        <reward_item>
          <item_id>28894</item_id>
          <num>3</num>
          <is_bind>1</is_bind>
        </reward_item>
        <reward_item>
          <item_id>26504</item_id>
          <num>30</num>
          <is_bind>1</is_bind>
        </reward_item>
      </reward_item_list>
    </data>
  </kill_rank_reward>
  <kill_title>
    <data>
      <kill_count>5</kill_count>
      <title_id>1</title_id>
    </data>
    <data>
      <kill_count>10</kill_count>
      <title_id>2</title_id>
    </data>
    <data>
      <kill_count>20</kill_count>
      <title_id>3</title_id>
    </data>
    <data>
      <kill_count>30</kill_count>
      <title_id>4</title_id>
    </data>
    <data>
      <kill_count>40</kill_count>
      <title_id>5</title_id>
    </data>
    <data>
      <kill_count>50</kill_count>
      <title_id>6</title_id>
    </data>
    <data>
      <kill_count>60</kill_count>
      <title_id>7</title_id>
    </data>
    <data>
      <kill_count>80</kill_count>
      <title_id>8</title_id>
    </data>
    <data>
      <kill_count>100</kill_count>
      <title_id>9</title_id>
    </data>
  </kill_title>
  <kill_score_reward>
    <data>
      <kill_score_min>99999</kill_score_min>
      <kill_score_max>100000</kill_score_max>
      <reward_shengwang>1</reward_shengwang>
    </data>
    <data>
      <kill_score_min>100001</kill_score_min>
      <kill_score_max>100002</kill_score_max>
      <reward_shengwang>2</reward_shengwang>
    </data>
    <data>
      <kill_score_min>100003</kill_score_min>
      <kill_score_max>100004</kill_score_max>
      <reward_shengwang>3</reward_shengwang>
    </data>
    <data>
      <kill_score_min>100005</kill_score_min>
      <kill_score_max>100006</kill_score_max>
      <reward_shengwang>4</reward_shengwang>
    </data>
  </kill_score_reward>
  <be_kill_reward>
    <data>
      <be_kill_times>1</be_kill_times>
      <add_maxhp_percent>100</add_maxhp_percent>
      <has_item_reward>0</has_item_reward>
      <reward_item>
        <item_id>0</item_id>
        <num></num>
        <is_bind></is_bind>
      </reward_item>
    </data>
    <data>
      <be_kill_times>2</be_kill_times>
      <add_maxhp_percent>150</add_maxhp_percent>
      <has_item_reward>0</has_item_reward>
      <reward_item>
        <item_id>0</item_id>
        <num></num>
        <is_bind></is_bind>
      </reward_item>
    </data>
    <data>
      <be_kill_times>3</be_kill_times>
      <add_maxhp_percent>200</add_maxhp_percent>
      <has_item_reward>0</has_item_reward>
      <reward_item>
        <item_id>0</item_id>
        <num></num>
        <is_bind></is_bind>
      </reward_item>
    </data>
    <data>
      <be_kill_times>4</be_kill_times>
      <add_maxhp_percent>220</add_maxhp_percent>
      <has_item_reward>0</has_item_reward>
      <reward_item>
        <item_id>0</item_id>
        <num></num>
        <is_bind></is_bind>
      </reward_item>
    </data>
    <data>
      <be_kill_times>5</be_kill_times>
      <add_maxhp_percent>250</add_maxhp_percent>
      <has_item_reward>0</has_item_reward>
      <reward_item>
        <item_id>0</item_id>
        <num></num>
        <is_bind></is_bind>
      </reward_item>
    </data>
    <data>
      <be_kill_times>6</be_kill_times>
      <add_maxhp_percent>280</add_maxhp_percent>
      <has_item_reward>0</has_item_reward>
      <reward_item>
        <item_id>0</item_id>
        <num></num>
        <is_bind></is_bind>
      </reward_item>
    </data>
    <data>
      <be_kill_times>7</be_kill_times>
      <add_maxhp_percent>300</add_maxhp_percent>
      <has_item_reward>0</has_item_reward>
      <reward_item>
        <item_id>0</item_id>
        <num></num>
        <is_bind></is_bind>
      </reward_item>
    </data>
    <data>
      <be_kill_times>8</be_kill_times>
      <add_maxhp_percent>300</add_maxhp_percent>
      <has_item_reward>0</has_item_reward>
      <reward_item>
        <item_id>0</item_id>
        <num></num>
        <is_bind></is_bind>
      </reward_item>
    </data>
  </be_kill_reward>
  <gather_pos>
    <data>
      <pos_x>65</pos_x>
      <pos_y>107</pos_y>
    </data>
    <data>
      <pos_x>66</pos_x>
      <pos_y>54</pos_y>
    </data>
    <data>
      <pos_x>32</pos_x>
      <pos_y>84</pos_y>
    </data>
    <data>
      <pos_x>98</pos_x>
      <pos_y>83</pos_y>
    </data>
    <data>
      <pos_x>47</pos_x>
      <pos_y>100</pos_y>
    </data>
    <data>
      <pos_x>82</pos_x>
      <pos_y>58</pos_y>
    </data>
    <data>
      <pos_x>41</pos_x>
      <pos_y>62</pos_y>
    </data>
    <data>
      <pos_x>90</pos_x>
      <pos_y>98</pos_y>
    </data>
    <data>
      <pos_x>65</pos_x>
      <pos_y>92</pos_y>
    </data>
    <data>
      <pos_x>66</pos_x>
      <pos_y>69</pos_y>
    </data>
    <data>
      <pos_x>47</pos_x>
      <pos_y>84</pos_y>
    </data>
    <data>
      <pos_x>83</pos_x>
      <pos_y>83</pos_y>
    </data>
    <data>
      <pos_x>57</pos_x>
      <pos_y>90</pos_y>
    </data>
    <data>
      <pos_x>72</pos_x>
      <pos_y>68</pos_y>
    </data>
    <data>
      <pos_x>51</pos_x>
      <pos_y>72</pos_y>
    </data>
    <data>
      <pos_x>80</pos_x>
      <pos_y>88</pos_y>
    </data>
    <data>
      <pos_x>65</pos_x>
      <pos_y>77</pos_y>
    </data>
    <data>
      <pos_x>66</pos_x>
      <pos_y>84</pos_y>
    </data>
    <data>
      <pos_x>62</pos_x>
      <pos_y>84</pos_y>
    </data>
    <data>
      <pos_x>68</pos_x>
      <pos_y>83</pos_y>
    </data>
    <data>
      <pos_x>67</pos_x>
      <pos_y>80</pos_y>
    </data>
    <data>
      <pos_x>62</pos_x>
      <pos_y>78</pos_y>
    </data>
    <data>
      <pos_x>61</pos_x>
      <pos_y>82</pos_y>
    </data>
    <data>
      <pos_x>70</pos_x>
      <pos_y>78</pos_y>
    </data>
    <data>
      <pos_x>65</pos_x>
      <pos_y>62</pos_y>
    </data>
    <data>
      <pos_x>66</pos_x>
      <pos_y>99</pos_y>
    </data>
    <data>
      <pos_x>77</pos_x>
      <pos_y>84</pos_y>
    </data>
    <data>
      <pos_x>53</pos_x>
      <pos_y>83</pos_y>
    </data>
    <data>
      <pos_x>77</pos_x>
      <pos_y>70</pos_y>
    </data>
    <data>
      <pos_x>52</pos_x>
      <pos_y>88</pos_y>
    </data>
    <data>
      <pos_x>71</pos_x>
      <pos_y>92</pos_y>
    </data>
    <data>
      <pos_x>60</pos_x>
      <pos_y>68</pos_y>
    </data>
  </gather_pos>
  <gather_buff>
    <data>
      <buff_seq>1</buff_seq>
      <buff_pro>1000</buff_pro>
      <buff_type>0</buff_type>
      <param_1>5000</param_1>
      <param_2>2000</param_2>
      <param_3>0</param_3>
      <param_4>0</param_4>
      <is_notice>1</is_notice>
    </data>
    <data>
      <buff_seq>2</buff_seq>
      <buff_pro>1000</buff_pro>
      <buff_type>1</buff_type>
      <param_1>3000</param_1>
      <param_2>5000</param_2>
      <param_3>0</param_3>
      <param_4>0</param_4>
      <is_notice>0</is_notice>
    </data>
    <data>
      <buff_seq>3</buff_seq>
      <buff_pro>1000</buff_pro>
      <buff_type>2</buff_type>
      <param_1>5000</param_1>
      <param_2>2000</param_2>
      <param_3>0</param_3>
      <param_4>0</param_4>
      <is_notice>1</is_notice>
    </data>
    <data>
      <buff_seq>4</buff_seq>
      <buff_pro>1000</buff_pro>
      <buff_type>3</buff_type>
      <param_1>3000</param_1>
      <param_2>5000</param_2>
      <param_3>0</param_3>
      <param_4>0</param_4>
      <is_notice>0</is_notice>
    </data>
    <data>
      <buff_seq>5</buff_seq>
      <buff_pro>1000</buff_pro>
      <buff_type>4</buff_type>
      <param_1>5000</param_1>
      <param_2>2000</param_2>
      <param_3>0</param_3>
      <param_4>0</param_4>
      <is_notice>1</is_notice>
    </data>
    <data>
      <buff_seq>6</buff_seq>
      <buff_pro>1000</buff_pro>
      <buff_type>5</buff_type>
      <param_1>3000</param_1>
      <param_2>5000</param_2>
      <param_3>0</param_3>
      <param_4>0</param_4>
      <is_notice>0</is_notice>
    </data>
    <data>
      <buff_seq>7</buff_seq>
      <buff_pro>1000</buff_pro>
      <buff_type>6</buff_type>
      <param_1>5000</param_1>
      <param_2>1000</param_2>
      <param_3>0</param_3>
      <param_4>0</param_4>
      <is_notice>1</is_notice>
    </data>
    <data>
      <buff_seq>8</buff_seq>
      <buff_pro>1000</buff_pro>
      <buff_type>7</buff_type>
      <param_1>3000</param_1>
      <param_2>0</param_2>
      <param_3>0</param_3>
      <param_4>0</param_4>
      <is_notice>1</is_notice>
    </data>
    <data>
      <buff_seq>9</buff_seq>
      <buff_pro>1000</buff_pro>
      <buff_type>8</buff_type>
      <param_1>3000</param_1>
      <param_2>0</param_2>
      <param_3>3000</param_3>
      <param_4>5000</param_4>
      <is_notice>0</is_notice>
    </data>
    <data>
      <buff_seq>10</buff_seq>
      <buff_pro>1000</buff_pro>
      <buff_type>9</buff_type>
      <param_1>5000</param_1>
      <param_2>3000</param_2>
      <param_3>0</param_3>
      <param_4>0</param_4>
      <is_notice>1</is_notice>
    </data>
  </gather_buff>
  <rank_title>
    <data>
      <rank>0</rank>
      <title_id>7012</title_id>
    </data>
    <data>
      <rank>1</rank>
      <title_id>7013</title_id>
    </data>
    <data>
      <rank>2</rank>
      <title_id>7014</title_id>
    </data>
  </rank_title>
  <kill_num_reward>
    <data>
      <kill_count>2</kill_count>
      <reward_item_list>
        <reward_item>
          <item_id>22817</item_id>
          <num>1</num>
          <is_bind>1</is_bind>
        </reward_item>
        <reward_item>
          <item_id>28894</item_id>
          <num>1</num>
          <is_bind>1</is_bind>
        </reward_item>
      </reward_item_list>
    </data>
    <data>
      <kill_count>4</kill_count>
      <reward_item_list>
        <reward_item>
          <item_id>22817</item_id>
          <num>1</num>
          <is_bind>1</is_bind>
        </reward_item>
        <reward_item>
          <item_id>28894</item_id>
          <num>1</num>
          <is_bind>1</is_bind>
        </reward_item>
      </reward_item_list>
    </data>
    <data>
      <kill_count>6</kill_count>
      <reward_item_list>
        <reward_item>
          <item_id>22817</item_id>
          <num>1</num>
          <is_bind>1</is_bind>
        </reward_item>
        <reward_item>
          <item_id>28894</item_id>
          <num>1</num>
          <is_bind>1</is_bind>
        </reward_item>
      </reward_item_list>
    </data>
    <data>
      <kill_count>10</kill_count>
      <reward_item_list>
        <reward_item>
          <item_id>22817</item_id>
          <num>1</num>
          <is_bind>1</is_bind>
        </reward_item>
        <reward_item>
          <item_id>28894</item_id>
          <num>1</num>
          <is_bind>1</is_bind>
        </reward_item>
      </reward_item_list>
    </data>
    <data>
      <kill_count>16</kill_count>
      <reward_item_list>
        <reward_item>
          <item_id>22818</item_id>
          <num>1</num>
          <is_bind>1</is_bind>
        </reward_item>
        <reward_item>
          <item_id>28894</item_id>
          <num>1</num>
          <is_bind>1</is_bind>
        </reward_item>
      </reward_item_list>
    </data>
  </kill_num_reward>
</config>
