<?xml version="1.0" encoding="utf-8"?>
<drop>
  <drop_id>5030</drop_id>
  <drop_item_prob_list>
    <drop_item_prob>
      <item_id>181</item_id>
      <is_bind>0</is_bind>
      <prob>416</prob>
      <num>1</num>
      <broadcast>0</broadcast>
    </drop_item_prob>
    <drop_item_prob>
      <item_id>1181</item_id>
      <is_bind>0</is_bind>
      <prob>416</prob>
      <num>1</num>
      <broadcast>0</broadcast>
    </drop_item_prob>
    <drop_item_prob>
      <item_id>2181</item_id>
      <is_bind>0</is_bind>
      <prob>416</prob>
      <num>1</num>
      <broadcast>0</broadcast>
    </drop_item_prob>
    <drop_item_prob>
      <item_id>3181</item_id>
      <is_bind>0</is_bind>
      <prob>416</prob>
      <num>1</num>
      <broadcast>0</broadcast>
    </drop_item_prob>
    <drop_item_prob>
      <item_id>4181</item_id>
      <is_bind>0</is_bind>
      <prob>416</prob>
      <num>1</num>
      <broadcast>0</broadcast>
    </drop_item_prob>
    <drop_item_prob>
      <item_id>5181</item_id>
      <is_bind>0</is_bind>
      <prob>416</prob>
      <num>1</num>
      <broadcast>0</broadcast>
    </drop_item_prob>
    <drop_item_prob>
      <item_id>6181</item_id>
      <is_bind>0</is_bind>
      <prob>416</prob>
      <num>1</num>
      <broadcast>0</broadcast>
    </drop_item_prob>
    <drop_item_prob>
      <item_id>8181</item_id>
      <is_bind>0</is_bind>
      <prob>416</prob>
      <num>1</num>
      <broadcast>0</broadcast>
    </drop_item_prob>
    <drop_item_prob>
      <item_id>281</item_id>
      <is_bind>0</is_bind>
      <prob>416</prob>
      <num>1</num>
      <broadcast>0</broadcast>
    </drop_item_prob>
    <drop_item_prob>
      <item_id>1281</item_id>
      <is_bind>0</is_bind>
      <prob>416</prob>
      <num>1</num>
      <broadcast>0</broadcast>
    </drop_item_prob>
    <drop_item_prob>
      <item_id>2281</item_id>
      <is_bind>0</is_bind>
      <prob>416</prob>
      <num>1</num>
      <broadcast>0</broadcast>
    </drop_item_prob>
    <drop_item_prob>
      <item_id>3281</item_id>
      <is_bind>0</is_bind>
      <prob>416</prob>
      <num>1</num>
      <broadcast>0</broadcast>
    </drop_item_prob>
    <drop_item_prob>
      <item_id>4281</item_id>
      <is_bind>0</is_bind>
      <prob>416</prob>
      <num>1</num>
      <broadcast>0</broadcast>
    </drop_item_prob>
    <drop_item_prob>
      <item_id>5281</item_id>
      <is_bind>0</is_bind>
      <prob>416</prob>
      <num>1</num>
      <broadcast>0</broadcast>
    </drop_item_prob>
    <drop_item_prob>
      <item_id>6281</item_id>
      <is_bind>0</is_bind>
      <prob>416</prob>
      <num>1</num>
      <broadcast>0</broadcast>
    </drop_item_prob>
    <drop_item_prob>
      <item_id>8281</item_id>
      <is_bind>0</is_bind>
      <prob>416</prob>
      <num>1</num>
      <broadcast>0</broadcast>
    </drop_item_prob>
    <drop_item_prob>
      <item_id>381</item_id>
      <is_bind>0</is_bind>
      <prob>416</prob>
      <num>1</num>
      <broadcast>0</broadcast>
    </drop_item_prob>
    <drop_item_prob>
      <item_id>1381</item_id>
      <is_bind>0</is_bind>
      <prob>416</prob>
      <num>1</num>
      <broadcast>0</broadcast>
    </drop_item_prob>
    <drop_item_prob>
      <item_id>2381</item_id>
      <is_bind>0</is_bind>
      <prob>416</prob>
      <num>1</num>
      <broadcast>0</broadcast>
    </drop_item_prob>
    <drop_item_prob>
      <item_id>3381</item_id>
      <is_bind>0</is_bind>
      <prob>416</prob>
      <num>1</num>
      <broadcast>0</broadcast>
    </drop_item_prob>
    <drop_item_prob>
      <item_id>4381</item_id>
      <is_bind>0</is_bind>
      <prob>416</prob>
      <num>1</num>
      <broadcast>0</broadcast>
    </drop_item_prob>
    <drop_item_prob>
      <item_id>5381</item_id>
      <is_bind>0</is_bind>
      <prob>416</prob>
      <num>1</num>
      <broadcast>0</broadcast>
    </drop_item_prob>
    <drop_item_prob>
      <item_id>6381</item_id>
      <is_bind>0</is_bind>
      <prob>416</prob>
      <num>1</num>
      <broadcast>0</broadcast>
    </drop_item_prob>
    <drop_item_prob>
      <item_id>8381</item_id>
      <is_bind>0</is_bind>
      <prob>416</prob>
      <num>1</num>
      <broadcast>0</broadcast>
    </drop_item_prob>
  </drop_item_prob_list>
</drop>
